defix_package_logger/__init__.py
defix_package_logger/json_formatter.py
defix_package_logger/string_formatter.py
defix_package_logger-0.1.12.dist-info/METADATA
defix_package_logger-0.1.12.dist-info/WHEEL
defix_package_logger-0.1.12.dist-info/entry_points.txt
defix_package_logger-0.1.12.dist-info/RECORD
